impossible/__init__.py
impossible_worlds-0.0.3.dist-info/METADATA
impossible_worlds-0.0.3.dist-info/WHEEL
impossible_worlds-0.0.3.dist-info/top_level.txt
impossible_worlds-0.0.3.dist-info/RECORD
