Metadata-Version: 2.4
Name: impossible-worlds
Version: 0.0.3
Summary: My Private Ufone API Library
Author: Nothing Is Impossible
Author-email: marslansalfias@mail.com
Requires-Dist: requests
Dynamic: author
Dynamic: author-email
Dynamic: requires-dist
Dynamic: summary
